gau_tensorflow/__init__.py
gau_tensorflow/gau_tensorflow.py
gau_tensorflow-0.0.1.dist-info/LICENSE
gau_tensorflow-0.0.1.dist-info/METADATA
gau_tensorflow-0.0.1.dist-info/WHEEL
gau_tensorflow-0.0.1.dist-info/top_level.txt
gau_tensorflow-0.0.1.dist-info/RECORD
