Metadata-Version: 2.1
Name: gau-tensorflow
Version: 0.0.1
Summary: Tensorflow implementation of Gated Attention Unit
Author: kevinyecs
Author-email: <kevinyecodes@gmail.com>
Keywords: python,gau,ml,tensorflow,gated attention unit,transformer
Classifier: Development Status :: 1 - Planning
Classifier: Intended Audience :: Developers
Classifier: Programming Language :: Python :: 3
Classifier: Operating System :: Unix
Classifier: Operating System :: MacOS :: MacOS X
Classifier: Operating System :: Microsoft :: Windows
License-File: LICENSE
Requires-Dist: tensorflow
